cgtcheck/__init__.py
cgtcheck/dummy.py
cgtcheck-0.0.3.dist-info/METADATA
cgtcheck-0.0.3.dist-info/WHEEL
cgtcheck-0.0.3.dist-info/licenses/LICENSE
cgtcheck-0.0.3.dist-info/RECORD
